{"properties": [
  {
    "name": "menu.dosarate",
    "type": "java.lang.String",
    "description": "A description for 'menu.dosarate'"
  },
  {
    "name": "menu.idlyrate",
    "type": "java.lang.String",
    "description": "A description for 'menu.idlyrate'"
  },
  {
    "name": "customer.name",
    "type": "java.lang.String",
    "description": "A description for 'customer.name'"
  },
  {
    "name": "menu.poharate",
    "type": "java.lang.String",
    "description": "A description for 'menu.poharate'"
  },
  {
    "name": "menu.vprate",
    "type": "java.lang.String",
    "description": "A description for 'menu.vprate'"
  },
  {
    "name": "hotel.name",
    "type": "java.lang.String",
    "description": "A description for 'hotel.name'"
  },
  {
    "name": "hotel.addrs",
    "type": "java.lang.String",
    "description": "A description for 'hotel.addrs'"
  },
  {
    "name": "hotel.contactno",
    "type": "java.lang.String",
    "description": "A description for 'hotel.contactno'"
  }
]}